dokumetry/__helpers.py
dokumetry/__init__.py
dokumetry/anthropic.py
dokumetry/async_anthropic.py
dokumetry/async_azure_openai.py
dokumetry/async_mistral.py
dokumetry/async_openai.py
dokumetry/azure_openai.py
dokumetry/cohere.py
dokumetry/mistral.py
dokumetry/openai.py
dokumetry-0.1.2.dist-info/LICENSE
dokumetry-0.1.2.dist-info/METADATA
dokumetry-0.1.2.dist-info/WHEEL
dokumetry-0.1.2.dist-info/RECORD
