Metadata-Version: 2.1
Name: dokumetry
Version: 0.1.2
Summary: A Python library for tracking LLM and GenAI usage and sending the usage data to Doku
Home-page: https://github.com/dokulabs/dokumetry-python
Keywords: openai,anthropic,claude,cohere,llm monitoring,observability,monitoring,gpt,Generative AI,chatGPT
Author: Doku Labs
Requires-Python: >=3.7.1,<4.0.0
Classifier: Programming Language :: Python :: 3
Classifier: Programming Language :: Python :: 3.8
Classifier: Programming Language :: Python :: 3.9
Classifier: Programming Language :: Python :: 3.10
Classifier: Programming Language :: Python :: 3.11
Classifier: Programming Language :: Python :: 3.12
Requires-Dist: anthropic (>=0.19.0,<0.20.0)
Requires-Dist: mistralai (>=0.1.5,<0.2.0)
Requires-Dist: openai (>=1.1.0,<2.0.0)
Requires-Dist: requests (>=2.26.0,<3.0.0)
Project-URL: Repository, https://github.com/dokulabs/dokumetry-python
